llm_evaluator/__init__.py
llm_evaluator/academic_baselines.py
llm_evaluator/cli.py
llm_evaluator/config.py
llm_evaluator/dataset_loaders.py
llm_evaluator/error_analysis.py
llm_evaluator/evaluator.py
llm_evaluator/export.py
llm_evaluator/metrics.py
llm_evaluator/statistical_metrics.py
llm_evaluator/system_info.py
llm_evaluator/visualizations.py
llm_evaluator/benchmarks/__init__.py
llm_evaluator/benchmarks/arc.py
llm_evaluator/benchmarks/base.py
llm_evaluator/benchmarks/boolq.py
llm_evaluator/benchmarks/commonsenseqa.py
llm_evaluator/benchmarks/donotanswer.py
llm_evaluator/benchmarks/gsm8k.py
llm_evaluator/benchmarks/hellaswag.py
llm_evaluator/benchmarks/mmlu.py
llm_evaluator/benchmarks/runner.py
llm_evaluator/benchmarks/safetybench.py
llm_evaluator/benchmarks/truthfulqa.py
llm_evaluator/benchmarks/winogrande.py
llm_evaluator/dashboard/__init__.py
llm_evaluator/dashboard/__main__.py
llm_evaluator/dashboard/app.py
llm_evaluator/dashboard/model_discovery.py
llm_evaluator/dashboard/models.py
llm_evaluator/dashboard/runner.py
llm_evaluator/dashboard/static/favicon.svg
llm_evaluator/dashboard/static/index.html
llm_evaluator/dashboard/static/assets/index-CcvlFRmM.js
llm_evaluator/dashboard/static/assets/index-DE0Rg7o1.css
llm_evaluator/providers/__init__.py
llm_evaluator/providers/anthropic_provider.py
llm_evaluator/providers/base.py
llm_evaluator/providers/cached_provider.py
llm_evaluator/providers/deepseek_provider.py
llm_evaluator/providers/fireworks_provider.py
llm_evaluator/providers/gemini_provider.py
llm_evaluator/providers/groq_provider.py
llm_evaluator/providers/huggingface_provider.py
llm_evaluator/providers/ollama_provider.py
llm_evaluator/providers/openai_provider.py
llm_evaluator/providers/together_provider.py
llm_evaluator/security/__init__.py
llm_evaluator/security/pii_detector.py
llm_evaluator/security/prompt_injection.py
llm_evaluator/security/red_team.py
llm_evaluator/security/toxicity.py
llm_benchmark_toolkit-2.4.2.dist-info/METADATA
llm_benchmark_toolkit-2.4.2.dist-info/WHEEL
llm_benchmark_toolkit-2.4.2.dist-info/entry_points.txt
llm_benchmark_toolkit-2.4.2.dist-info/top_level.txt
llm_benchmark_toolkit-2.4.2.dist-info/RECORD
