Metadata-Version: 2.4
Name: llm-benchmark-toolkit
Version: 2.4.2
Summary: Benchmark LLMs with 10 benchmarks & 132K+ questions. 8 providers: OpenAI, Anthropic, Groq, Together, Fireworks, DeepSeek, Ollama, HuggingFace. Unified CLI + Web dashboard.
Author-email: Nahuel Giudizi <nahuelgiudizi@hotmail.com>
License-Expression: MIT
Project-URL: Homepage, https://github.com/NahuelGiudizi/llm-evaluation
Project-URL: Repository, https://github.com/NahuelGiudizi/llm-evaluation
Project-URL: Issues, https://github.com/NahuelGiudizi/llm-evaluation/issues
Project-URL: Blog, https://dev.to/nahuelgiudizi/building-an-honest-llm-evaluation-framework-from-fake-metrics-to-real-benchmarks-2b90
Project-URL: PyPI, https://pypi.org/project/llm-benchmark-toolkit/
Keywords: llm,evaluation,benchmark,mmlu,truthfulqa,hellaswag,arc,winogrande,commonsenseqa,boolq,safetybench,gpt,gpt-4,gpt-4o,claude,ollama,openai,anthropic,ai,machine-learning,deep-learning,nlp,language-model,dashboard,academic,research,testing,metrics,llama,mistral,gemini,cohere,together-ai,model-comparison,performance-testing,ml-ops,mlops
Classifier: Development Status :: 5 - Production/Stable
Classifier: Intended Audience :: Developers
Classifier: Intended Audience :: Science/Research
Classifier: Intended Audience :: Education
Classifier: Programming Language :: Python :: 3
Classifier: Programming Language :: Python :: 3.11
Classifier: Programming Language :: Python :: 3.12
Classifier: Programming Language :: Python :: 3.13
Classifier: Topic :: Scientific/Engineering :: Artificial Intelligence
Classifier: Topic :: Software Development :: Testing
Classifier: Framework :: FastAPI
Classifier: Environment :: Web Environment
Classifier: Natural Language :: English
Classifier: Natural Language :: Spanish
Requires-Python: >=3.11
Requires-Dist: ollama>=0.1.0
Requires-Dist: datasets>=2.14.0
Requires-Dist: scikit-learn>=1.3.0
Requires-Dist: numpy>=1.24.0
Requires-Dist: pandas>=2.0.0
Requires-Dist: matplotlib>=3.7.0
Requires-Dist: plotly>=5.17.0
Requires-Dist: seaborn>=0.12.0
Requires-Dist: scipy>=1.11.0
Requires-Dist: click>=8.1.0
Requires-Dist: pydantic>=2.0.0
Requires-Dist: pydantic-settings>=2.0.0
Requires-Dist: psutil>=5.9.0
Requires-Dist: tqdm>=4.66.0
Requires-Dist: fastapi>=0.104.0
Requires-Dist: uvicorn[standard]>=0.24.0
Requires-Dist: sse-starlette>=1.8.0
Requires-Dist: openai>=1.0.0
Requires-Dist: anthropic>=0.18.0
Requires-Dist: huggingface-hub>=0.20.0
Provides-Extra: dev
Requires-Dist: pytest>=7.4.0; extra == "dev"
Requires-Dist: pytest-cov>=4.1.0; extra == "dev"
Requires-Dist: pytest-mock>=3.12.0; extra == "dev"
Requires-Dist: black>=23.0.0; extra == "dev"
Requires-Dist: flake8>=6.0.0; extra == "dev"
Requires-Dist: ruff>=0.1.0; extra == "dev"
Requires-Dist: mypy>=1.8.0; extra == "dev"
Requires-Dist: types-requests>=2.31.0; extra == "dev"
Provides-Extra: notebooks
Requires-Dist: jupyter>=1.0.0; extra == "notebooks"
Requires-Dist: ipykernel>=6.25.0; extra == "notebooks"
Requires-Dist: ipywidgets>=8.1.0; extra == "notebooks"
Provides-Extra: openai
Requires-Dist: openai>=1.0.0; extra == "openai"
Provides-Extra: anthropic
Requires-Dist: anthropic>=0.18.0; extra == "anthropic"
Provides-Extra: huggingface
Requires-Dist: huggingface-hub>=0.20.0; extra == "huggingface"
Provides-Extra: all-providers
Requires-Dist: openai>=1.0.0; extra == "all-providers"
Requires-Dist: anthropic>=0.18.0; extra == "all-providers"
Requires-Dist: huggingface-hub>=0.20.0; extra == "all-providers"
Provides-Extra: dashboard
Requires-Dist: fastapi>=0.104.0; extra == "dashboard"
Requires-Dist: uvicorn[standard]>=0.24.0; extra == "dashboard"
Requires-Dist: sse-starlette>=1.8.0; extra == "dashboard"
Provides-Extra: full
Requires-Dist: openai>=1.0.0; extra == "full"
Requires-Dist: anthropic>=0.18.0; extra == "full"
Requires-Dist: huggingface-hub>=0.20.0; extra == "full"
Requires-Dist: fastapi>=0.104.0; extra == "full"
Requires-Dist: uvicorn[standard]>=0.24.0; extra == "full"
Requires-Dist: sse-starlette>=1.8.0; extra == "full"
Provides-Extra: all
Requires-Dist: openai>=1.0.0; extra == "all"
Requires-Dist: anthropic>=0.18.0; extra == "all"
Requires-Dist: huggingface-hub>=0.20.0; extra == "all"
Requires-Dist: fastapi>=0.104.0; extra == "all"
Requires-Dist: uvicorn[standard]>=0.24.0; extra == "all"
Requires-Dist: sse-starlette>=1.8.0; extra == "all"
Requires-Dist: jupyter>=1.0.0; extra == "all"
Requires-Dist: ipykernel>=6.25.0; extra == "all"
Dynamic: requires-python
